aggdraw.cpython-313-darwin.so
aggdraw-1.4.1.dist-info/RECORD
aggdraw-1.4.1.dist-info/WHEEL
aggdraw-1.4.1.dist-info/top_level.txt
aggdraw-1.4.1.dist-info/METADATA
aggdraw-1.4.1.dist-info/licenses/LICENSE.txt
aggdraw.dylibs/libpng16.16.dylib
aggdraw.dylibs/libfreetype.6.dylib
